ini2toml/__init__.py
ini2toml/__main__.py
ini2toml/api.py
ini2toml/base_translator.py
ini2toml/cli.py
ini2toml/errors.py
ini2toml/intermediate_repr.py
ini2toml/profile.py
ini2toml/py.typed
ini2toml/transformations.py
ini2toml/translator.py
ini2toml/types.py
ini2toml/drivers/__init__.py
ini2toml/drivers/configparser.py
ini2toml/drivers/configupdater.py
ini2toml/drivers/full_toml.py
ini2toml/drivers/lite_toml.py
ini2toml/drivers/plain_builtins.py
ini2toml/plugins/__init__.py
ini2toml/plugins/best_effort.py
ini2toml/plugins/coverage.py
ini2toml/plugins/isort.py
ini2toml/plugins/mypy.py
ini2toml/plugins/profile_independent_tasks.py
ini2toml/plugins/pytest.py
ini2toml/plugins/setuptools_pep621.py
ini2toml/plugins/toml_incompatibilities.py
ini2toml-0.14.dist-info/LICENSE.txt
ini2toml-0.14.dist-info/METADATA
ini2toml-0.14.dist-info/WHEEL
ini2toml-0.14.dist-info/entry_points.txt
ini2toml-0.14.dist-info/top_level.txt
ini2toml-0.14.dist-info/RECORD
