Metadata-Version: 2.1
Name: ini2toml
Version: 0.14
Summary: Automatically conversion of .ini/.cfg files to TOML equivalents
Home-page: https://github.com/abravalheri/ini2toml/
Author: Anderson Bravalheri
Author-email: andersonbravalheri@gmail.com
License: MPL-2.0
Project-URL: Documentation, https://ini2toml.readthedocs.io/
Project-URL: Source, https://github.com/abravalheri/ini2toml
Project-URL: Tracker, https://github.com/abravalheri/ini2toml/issues
Project-URL: Changelog, https://ini2toml.readthedocs.io/en/latest/changelog.html
Project-URL: Download, https://pypi.org/project/ini2toml/#files
Platform: any
Classifier: Development Status :: 4 - Beta
Classifier: Programming Language :: Python
License-File: LICENSE.txt
Requires-Dist: packaging >=20.7
Requires-Dist: setuptools >=59.6
Provides-Extra: all
Requires-Dist: configupdater <4,>=3.0.1 ; extra == 'all'
Requires-Dist: tomlkit <2,>=0.10.0 ; extra == 'all'
Requires-Dist: tomli-w <2,>=0.4.0 ; extra == 'all'
Provides-Extra: experimental
Requires-Dist: pyproject-fmt >=0.4.0 ; (python_version >= "3.7") and extra == 'experimental'
Provides-Extra: full
Requires-Dist: configupdater <4,>=3.0.1 ; extra == 'full'
Requires-Dist: tomlkit <2,>=0.10.0 ; extra == 'full'
Requires-Dist: importlib-metadata ; (python_version < "3.8") and extra == 'full'
Provides-Extra: lite
Requires-Dist: tomli-w <2,>=0.4.0 ; extra == 'lite'
Requires-Dist: importlib-metadata ; (python_version < "3.8") and extra == 'lite'
Provides-Extra: testing
Requires-Dist: isort ; extra == 'testing'
Requires-Dist: setuptools ; extra == 'testing'
Requires-Dist: tomli ; extra == 'testing'
Requires-Dist: pytest ; extra == 'testing'
Requires-Dist: pytest-cov ; extra == 'testing'
Requires-Dist: pytest-xdist ; extra == 'testing'
Requires-Dist: pytest-randomly ; extra == 'testing'
Requires-Dist: validate-pyproject <2,>=0.6 ; extra == 'testing'
Provides-Extra: typechecking
Requires-Dist: typing-extensions ; (python_version < "3.8") and extra == 'typechecking'
